marsys/__init__.py
marsys/agents/__init__.py
marsys/agents/agent_pool.py
marsys/agents/agents.py
marsys/agents/browser_agent.py
marsys/agents/browser_agent_legacy.py
marsys/agents/browser_agent_legacy2.py
marsys/agents/exceptions.py
marsys/agents/file_operation_agent.py
marsys/agents/learnable_agents.py
marsys/agents/memory.py
marsys/agents/memory_strategies.py
marsys/agents/pool_factory.py
marsys/agents/registry.py
marsys/agents/utils.py
marsys/agents/web_search_agent.py
marsys/coordination/__init__.py
marsys/coordination/config.py
marsys/coordination/context_manager.py
marsys/coordination/event_bus.py
marsys/coordination/orchestra.py
marsys/coordination/branches/__init__.py
marsys/coordination/branches/types.py
marsys/coordination/communication/__init__.py
marsys/coordination/communication/core.py
marsys/coordination/communication/manager.py
marsys/coordination/communication/user_node_handler.py
marsys/coordination/communication/channels/__init__.py
marsys/coordination/communication/channels/enhanced_terminal.py
marsys/coordination/communication/channels/terminal.py
marsys/coordination/communication/channels/web.py
marsys/coordination/configs/__init__.py
marsys/coordination/configs/auto_run.py
marsys/coordination/execution/__init__.py
marsys/coordination/execution/branch_executor.py
marsys/coordination/execution/branch_spawner.py
marsys/coordination/execution/step_executor.py
marsys/coordination/execution/tool_executor.py
marsys/coordination/routing/__init__.py
marsys/coordination/routing/router.py
marsys/coordination/routing/types.py
marsys/coordination/rules/__init__.py
marsys/coordination/rules/basic_rules.py
marsys/coordination/rules/rule_factory.py
marsys/coordination/rules/rules_engine.py
marsys/coordination/state/__init__.py
marsys/coordination/state/checkpoint.py
marsys/coordination/state/state_manager.py
marsys/coordination/status/__init__.py
marsys/coordination/status/channels.py
marsys/coordination/status/events.py
marsys/coordination/status/manager.py
marsys-0.1.2.dist-info/licenses/AUTHORS
marsys-0.1.2.dist-info/licenses/LICENSE
marsys-0.1.2.dist-info/METADATA
marsys-0.1.2.dist-info/WHEEL
marsys-0.1.2.dist-info/top_level.txt
marsys-0.1.2.dist-info/RECORD
