Metadata-Version: 2.4
Name: marsys
Version: 0.1.2
Summary: A powerful framework for orchestrating collaborative AI agents with sophisticated reasoning, planning, and autonomous capabilities
Home-page: https://github.com/rezaho/MARSYS
Author: Reza Hosseini
Author-email: Reza Hosseini <reza@marsys.ai>
Maintainer: Reza Hosseini
Maintainer-email: Reza Hosseini <reza@marsys.ai>
License: Apache-2.0
Project-URL: Homepage, https://marsys.ai
Project-URL: Documentation, https://marsys.ai
Project-URL: Repository, https://github.com/rezaho/MARSYS
Project-URL: Issues, https://github.com/rezaho/MARSYS/issues
Project-URL: Changelog, https://github.com/rezaho/MARSYS/blob/main/CHANGELOG.md
Project-URL: Discussions, https://github.com/rezaho/MARSYS/discussions
Keywords: ai,agents,multi-agent,llm,orchestration,coordination,reasoning,planning,autonomous,openai,anthropic,claude,gpt,gemini,multi-agent-systems,agent-framework,ai-agents
Classifier: Development Status :: 4 - Beta
Classifier: Intended Audience :: Developers
Classifier: Intended Audience :: Science/Research
Classifier: License :: OSI Approved :: Apache Software License
Classifier: Operating System :: OS Independent
Classifier: Programming Language :: Python :: 3
Classifier: Programming Language :: Python :: 3.12
Classifier: Programming Language :: Python :: 3.13
Classifier: Topic :: Scientific/Engineering :: Artificial Intelligence
Classifier: Topic :: Software Development :: Libraries :: Python Modules
Classifier: Framework :: AsyncIO
Requires-Python: >=3.12
License-File: LICENSE
License-File: AUTHORS
Requires-Dist: pydantic>=2.11.9
Requires-Dist: requests>=2.32.3
Requires-Dist: psutil>=7.1.0
Requires-Dist: packaging>=25.0
Requires-Dist: aiohttp>=3.12.15
Requires-Dist: pyyaml>=6.0.2
Requires-Dist: python-dotenv>=1.0.0
Requires-Dist: playwright>=1.55.0
Requires-Dist: pillow>=12.0.0
Requires-Dist: beautifulsoup4>=4.14.2
Requires-Dist: lxml>=6.0.2
Requires-Dist: brotli>=1.1.0
Requires-Dist: markdownify>=1.2.0
Requires-Dist: rich>=14.1.0
Requires-Dist: textual>=6.2.0
Requires-Dist: python-dateutil>=2.9.0
Requires-Dist: pypdf>=3.0.0
Requires-Dist: googlesearch-python>=1.3.0
Requires-Dist: PyMuPDF>=1.26.0
Requires-Dist: chardet>=5.2.0
Requires-Dist: structlog>=25.4.0
Requires-Dist: python-json-logger>=2.0.7
Requires-Dist: jsonschema>=4.23.0
Provides-Extra: local-models
Requires-Dist: torch>=2.6.0; extra == "local-models"
Requires-Dist: torchvision>=0.23.0; extra == "local-models"
Requires-Dist: transformers<5.0,>=4.54; extra == "local-models"
Requires-Dist: accelerate>=1.5.2; extra == "local-models"
Requires-Dist: peft>=0.17.1; extra == "local-models"
Requires-Dist: trl>=0.22.1; extra == "local-models"
Requires-Dist: datasets>=4.1.1; extra == "local-models"
Requires-Dist: decord>=0.6.0; extra == "local-models"
Requires-Dist: qwen-vl-utils>=0.0.8; extra == "local-models"
Provides-Extra: production
Requires-Dist: vllm>=0.10.2; extra == "production"
Requires-Dist: flash-attn>=2.7.4.post1; extra == "production"
Requires-Dist: triton>=3.4.0; extra == "production"
Requires-Dist: ninja>=1.13.0; extra == "production"
Provides-Extra: dev
Requires-Dist: torch>=2.6.0; extra == "dev"
Requires-Dist: torchvision>=0.23.0; extra == "dev"
Requires-Dist: transformers<5.0,>=4.54; extra == "dev"
Requires-Dist: accelerate>=1.5.2; extra == "dev"
Requires-Dist: peft>=0.17.1; extra == "dev"
Requires-Dist: trl>=0.22.1; extra == "dev"
Requires-Dist: datasets>=4.1.1; extra == "dev"
Requires-Dist: decord>=0.6.0; extra == "dev"
Requires-Dist: qwen-vl-utils>=0.0.8; extra == "dev"
Requires-Dist: vllm>=0.10.2; extra == "dev"
Requires-Dist: flash-attn>=2.7.4.post1; extra == "dev"
Requires-Dist: triton>=3.4.0; extra == "dev"
Requires-Dist: ninja>=1.13.0; extra == "dev"
Requires-Dist: pytest>=8.4.1; extra == "dev"
Requires-Dist: pytest-asyncio>=1.0.0; extra == "dev"
Requires-Dist: pytest-mock>=3.14.1; extra == "dev"
Requires-Dist: pytest-cov>=6.2.1; extra == "dev"
Requires-Dist: black>=25.0.0; extra == "dev"
Requires-Dist: flake8>=7.1.0; extra == "dev"
Requires-Dist: mypy>=1.13.0; extra == "dev"
Requires-Dist: mkdocs>=1.6.1; extra == "dev"
Requires-Dist: mkdocs-material>=9.6.21; extra == "dev"
Requires-Dist: mkdocstrings>=0.30.1; extra == "dev"
Requires-Dist: mkdocstrings-python>=1.18.2; extra == "dev"
Dynamic: author
Dynamic: home-page
Dynamic: license-file
Dynamic: maintainer
Dynamic: requires-python
